MANIFEST.in
README
setup.py
cookie_law/__init__.py
cookie_law/admin.py
cookie_law/functions.py
cookie_law/models.py
cookie_law/urls.py
cookie_law/views.py
cookie_law/migrations/0001_initial.py
cookie_law/migrations/0002_auto__add_cookiebar.py
cookie_law/migrations/0003_auto__add_field_cookiebar_button_title.py
cookie_law/migrations/0004_auto__add_field_cookiebar_title__add_field_cookiebar_language__del_uni.py
cookie_law/migrations/0005_add_field_close.py
cookie_law/migrations/__init__.py
cookie_law/templates/cookie_law/_base_include.html
cookie_law/templatetags/__init__.py
cookie_law/templatetags/cookie_bar.py
django_cookie_law_nl.egg-info/PKG-INFO
django_cookie_law_nl.egg-info/SOURCES.txt
django_cookie_law_nl.egg-info/dependency_links.txt
django_cookie_law_nl.egg-info/top_level.txt