Metadata-Version: 1.0
Name: django-cookie-law-nl
Version: 0.2.1
Summary: Django specific cookie implementation compliant with Dutch law, use at your own risk.
Home-page: https://bitbucket.org/getlogic/lib_django_cookie_law
Author: Wouter Lansu
Author-email: wfrlansu@gmail.com
License: UNKNOWN
Platform: UNKNOWN
Classifier: Development Status :: 4 - Beta
Classifier: License :: OSI Approved :: BSD License
Classifier: Programming Language :: Python
Classifier: Framework :: Django
Classifier: Topic :: Internet
Classifier: Topic :: Software Development :: Libraries :: Python Modules
Classifier: Intended Audience :: Developers
